the_calc_pack_Pranav76/__init__.py
the_calc_pack_Pranav76/sim-calc.py
thecalcpack-1.0.0.dist-info/LICENSE.txt
thecalcpack-1.0.0.dist-info/METADATA
thecalcpack-1.0.0.dist-info/WHEEL
thecalcpack-1.0.0.dist-info/top_level.txt
thecalcpack-1.0.0.dist-info/RECORD
