Metadata-Version: 2.1
Name: thecalcpack
Version: 1.0.0
Summary: This package helps you to carry out basic arithmetic operations
Author: Pranav Gore
Author-email: pranavaudumber.gore2022@vitstudent.ac.in
Requires-Python: >=3.6
License-File: LICENSE.txt
